py_mc_lib/__init__.py
py_mc_lib/download/JavaClient.py
py_mc_lib/download/__init__.py
py_mc_lib/download/downloader.py
py_mc_lib/download/headers.py
py_mc_lib/download/packages.py
py_mc_lib/download/version_manifest.py
py_mc_lib/launcher/LauncherEvent.py
py_mc_lib/launcher/__init__.py
py_mc_lib/launcher/natives.py
py_mc_lib-0.1.2.dist-info/LICENSE
py_mc_lib-0.1.2.dist-info/METADATA
py_mc_lib-0.1.2.dist-info/WHEEL
py_mc_lib-0.1.2.dist-info/top_level.txt
py_mc_lib-0.1.2.dist-info/RECORD
