Metadata-Version: 2.1
Name: py-mc-lib
Version: 0.1.2
Summary: 一款专为简化Minecraft整合开发而设计的Python库。
Home-page: https://github.com/PYmili/py-mc-lib
Author: PYmili
Author-email: mc2005wj@163.com
Classifier: Programming Language :: Python :: 3
Classifier: License :: OSI Approved :: GNU General Public License v3 (GPLv3)
Classifier: Operating System :: OS Independent
Requires-Python: >=3.10
License-File: LICENSE
Requires-Dist: requests
Requires-Dist: loguru
